manyconfig/__init__.py
manyconfig/config.py
manyconfig/environment.py
manyconfig/file.py
manyconfig/manyconfig.py
manyconfig-1.0.0.dist-info/METADATA
manyconfig-1.0.0.dist-info/RECORD
manyconfig-1.0.0.dist-info/WHEEL
manyconfig-1.0.0.dist-info/top_level.txt
tests/__init__.py
tests/config.py
tests/conftest.py
tests/environment.py
tests/file.py
tests/test_manyconfig.py
