Metadata-Version: 2.1
Name: manyconfig
Version: 1.0.0
Summary: An easy-to-use declarative loader of configuration
Home-page: https://github.com/Shir0kamii/manyconfig
Author: Shir0kamii
Author-email: shir0kamii@gmail.com
License: UNKNOWN
Download-URL: https://github.com/Shir0kamii/manyconfig/tags
Platform: any
Classifier: Operating System :: POSIX :: Linux
Classifier: Programming Language :: Python
Classifier: Programming Language :: Python :: 2
Classifier: Programming Language :: Python :: 2.7
Classifier: Programming Language :: Python :: 3
Classifier: Programming Language :: Python :: 3.2
Classifier: Programming Language :: Python :: 3.3
Classifier: Programming Language :: Python :: 3.4
Classifier: Programming Language :: Python :: 3.5
Classifier: Topic :: Software Development :: Libraries :: Python Modules
